cocoroboai/__init__.py
cocorobo_ai_tool-0.1.42.dist-info/LICENSE
cocorobo_ai_tool-0.1.42.dist-info/METADATA
cocorobo_ai_tool-0.1.42.dist-info/WHEEL
cocorobo_ai_tool-0.1.42.dist-info/top_level.txt
cocorobo_ai_tool-0.1.42.dist-info/RECORD
