Metadata-Version: 2.1
Name: cocorobo-ai-tool
Version: 0.1.42
Summary: CocoRobo AI Training Tools
Home-page: http://cocorobo.cc
Author: Tommy Jing-Tao Liu
Author-email: tommy@cocorobo.cc
License: UNKNOWN
Project-URL: Bug Tracker, http://cocorobo.cc
Platform: UNKNOWN
Classifier: Programming Language :: Python :: 3
Classifier: License :: OSI Approved :: MIT License
Classifier: Operating System :: OS Independent
Requires-Python: >=3.6
License-File: LICENSE
